labml_app/.gitignore
labml_app/__init__.py
labml_app/analyses_settings.py
labml_app/analyses_settings.sample.py
labml_app/docs.py
labml_app/enums.py
labml_app/flask_app.py
labml_app/handlers.py
labml_app/settings.py
labml_app/settings.sample.py
labml_app/.idea/.gitignore
labml_app/.idea/labml_app.iml
labml_app/.idea/misc.xml
labml_app/.idea/modules.xml
labml_app/.idea/vcs.xml
labml_app/.idea/workspace.xml
labml_app/.idea/inspectionProfiles/Project_Default.xml
labml_app/.idea/inspectionProfiles/profiles_settings.xml
labml_app/analyses/__init__.py
labml_app/analyses/analysis.py
labml_app/analyses/helper.py
labml_app/analyses/logs.py
labml_app/analyses/preferences.py
labml_app/analyses/series.py
labml_app/analyses/series_collection.py
labml_app/analyses/computers/__init__.py
labml_app/analyses/computers/battery.py
labml_app/analyses/computers/cpu.py
labml_app/analyses/computers/disk.py
labml_app/analyses/computers/gpu.py
labml_app/analyses/computers/memory.py
labml_app/analyses/computers/network.py
labml_app/analyses/computers/process.py
labml_app/analyses/experiments/__init__.py
labml_app/analyses/experiments/comparison.py
labml_app/analyses/experiments/custom_metrics.py
labml_app/analyses/experiments/distributed_metrics.py
labml_app/analyses/experiments/metrics.py
labml_app/analyses/experiments/stderr.py
labml_app/analyses/experiments/stdlogger.py
labml_app/analyses/experiments/stdout.py
labml_app/auth/__init__.py
labml_app/db/__init__.py
labml_app/db/app_token.py
labml_app/db/computer.py
labml_app/db/folder.py
labml_app/db/project.py
labml_app/db/run.py
labml_app/db/session.py
labml_app/db/status.py
labml_app/db/user.py
labml_app/logger/__init__.py
labml_app/logger/logger.py
labml_app/scripts/fix_models.py
labml_app/static/favicon.ico
labml_app/static/index.html
labml_app/static/site.webmanifest
labml_app/static/css/style.css
labml_app/static/css/style.css.map
labml_app/static/images/android-chrome-192x192.png
labml_app/static/images/android-chrome-512x512.png
labml_app-0.5.14.dist-info/METADATA
labml_app-0.5.14.dist-info/WHEEL
labml_app-0.5.14.dist-info/top_level.txt
labml_app-0.5.14.dist-info/RECORD
