Metadata-Version: 2.1
Name: labml-app
Version: 0.5.14
Summary: Web app for https://github.com/labmlai/labml
Home-page: https://github.com/labmlai/labml
Author: labml.ai Team
Author-email: contact@labml.ai
Project-URL: Documentation, https://docs.labml.ai
Keywords: machine learning
Classifier: Programming Language :: Python :: 3
Classifier: License :: OSI Approved :: MIT License
Classifier: Intended Audience :: Developers
Classifier: Intended Audience :: Science/Research
Classifier: Topic :: Scientific/Engineering
Classifier: Topic :: Scientific/Engineering :: Mathematics
Classifier: Topic :: Scientific/Engineering :: Artificial Intelligence
Classifier: Topic :: Software Development
Classifier: Topic :: Software Development :: Libraries
Classifier: Topic :: Software Development :: Libraries :: Python Modules
Requires-Dist: labml (>=0.5.2)
Requires-Dist: gunicorn (>=22.0.0)
Requires-Dist: numpy
Requires-Dist: labml-db (>=0.0.15)
Requires-Dist: fastapi (>=0.111.0)
Requires-Dist: uvicorn (>=0.30.1)
Requires-Dist: pymongo (>=4.8.0)
